CHANGES.rst
DEVELOP.rst
LICENSE.rst
LICENSE_GPL.rst
MANIFEST.in
README.rst
setup.cfg
setup.py
src/collective/__init__.py
src/collective.instancebehavior.egg-info/PKG-INFO
src/collective.instancebehavior.egg-info/SOURCES.txt
src/collective.instancebehavior.egg-info/dependency_links.txt
src/collective.instancebehavior.egg-info/entry_points.txt
src/collective.instancebehavior.egg-info/namespace_packages.txt
src/collective.instancebehavior.egg-info/not-zip-safe
src/collective.instancebehavior.egg-info/requires.txt
src/collective.instancebehavior.egg-info/top_level.txt
src/collective/instancebehavior/__init__.py
src/collective/instancebehavior/configure.zcml
src/collective/instancebehavior/interfaces.py
src/collective/instancebehavior/tests/__init__.py
src/collective/instancebehavior/tests/test_instancebehavior.py