Metadata-Version: 2.1
Name: collective.instancebehavior
Version: 0.5
Summary: Enable behaviors per content type instance.
Home-page: https://pypi.python.org/pypi/collective.instancebehavior
Author: JC Brand, Johannes Raggam, Robert Niederreiter
Author-email: 
License: GNU General Public Licence
Keywords: Python Plone Dexterity Behavior Development
Platform: UNKNOWN
Classifier: Environment :: Web Environment
Classifier: Framework :: Plone
Classifier: Framework :: Plone :: 4.3
Classifier: Framework :: Plone :: 5.1
Classifier: Framework :: Plone :: 5.2
Classifier: License :: OSI Approved :: GNU General Public License (GPL)
Classifier: Operating System :: OS Independent
Classifier: Programming Language :: Python
Classifier: Programming Language :: Python :: 2.7
Classifier: Programming Language :: Python :: 3.6
Classifier: Programming Language :: Python :: 3.7
Classifier: Topic :: Internet :: WWW/HTTP :: Dynamic Content
Provides-Extra: test
